xronos_telemetry/__init__.py
xronos_telemetry/libopentelemetry_proto.so
xronos_telemetry/libopentelemetry_proto_grpc.so
xronos_telemetry/otel.cpython-311-aarch64-linux-gnu.so
xronos_telemetry/otel.pyi
xronos_telemetry/py.typed
xronos_telemetry-0.0.4.dist-info/licenses/THIRD_PARTY_NOTICE
xronos_telemetry-0.0.4.dist-info/licenses/LICENSES/LicenseRef-Xronos-Commercial-License-v1.txt
xronos_telemetry-0.0.4.dist-info/licenses/third-party-licenses/abseil_LICENSE
xronos_telemetry-0.0.4.dist-info/licenses/third-party-licenses/grpc_LICENSE
xronos_telemetry-0.0.4.dist-info/licenses/third-party-licenses/grpc_NOTICE
xronos_telemetry-0.0.4.dist-info/licenses/third-party-licenses/opentelemetry_cpp_LICENSE
xronos_telemetry-0.0.4.dist-info/licenses/third-party-licenses/opentelemetry_proto_LICENSE
xronos_telemetry-0.0.4.dist-info/licenses/third-party-licenses/protobuf_LICENSE
xronos_telemetry-0.0.4.dist-info/licenses/third-party-licenses/pybind11_LICENSE
xronos_telemetry-0.0.4.dist-info/METADATA
xronos_telemetry-0.0.4.dist-info/WHEEL
xronos_telemetry-0.0.4.dist-info/RECORD
