Metadata-Version: 2.1
Name: xronos-telemetry
Version: 0.0.4
Summary: telemetry backend for xronos
Author-Email: Christian Menard <christian@xronos.com>
License: Xronos Commercial License Agreement v1
Classifier: Development Status :: 3 - Alpha
Classifier: Intended Audience :: Developers
Classifier: Programming Language :: Python :: 3
Classifier: Programming Language :: Python :: 3.10
Classifier: Programming Language :: Python :: 3.11
Classifier: Programming Language :: Python :: 3.12
Classifier: Programming Language :: Python :: 3.13
Classifier: Operating System :: POSIX :: Linux
Classifier: Topic :: Scientific/Engineering
Classifier: Topic :: Software Development :: Embedded Systems
Classifier: Topic :: Software Development :: Libraries :: Application Frameworks
Classifier: Topic :: Software Development :: Libraries :: Python Modules
Classifier: Typing :: Typed
Project-URL: Homepage, https://xronos.com
Project-URL: Documentation, https://xronos-inc.github.io/xronos/index.html
Requires-Python: >=3.10
Requires-Dist: xronos==0.0.4
